Metadata-Version: 1.0
Name: gripit-capture
Version: 1.0.5
Summary: A webcam extension package for GripIt App - Add GOPRO Support
Home-page: http://github.com/agilefreaks
Author: Agilefreaks
Author-email: agilefreaks@agilefreaks.com
License: MIT
Platform: UNKNOWN
